wlalign/__init__.py
wlalign/alignment.py
wlalign/similarity.py
wlalign/utils.py
wlalign-1.0.1.data/scripts/wlalign
wlalign-1.0.1.dist-info/LICENSE
wlalign-1.0.1.dist-info/METADATA
wlalign-1.0.1.dist-info/WHEEL
wlalign-1.0.1.dist-info/top_level.txt
wlalign-1.0.1.dist-info/RECORD
