Metadata-Version: 2.1
Name: wlalign
Version: 1.0.1
Summary: A Python package that implements the WL-align algorithm that solves the graph alignment problem
Home-page: https://gitlab.inria.fr/brain-graph/wl-align
Author: Matteo Frigo, Emilio Cruciani, David Coudert, Rachid Deriche, Emanuele Natale, Samuel Deslauriers-Gauthier
License: UNKNOWN
Project-URL: Source, https://gitlab.inria.fr/brain-graph/wl-align
Project-URL: Bug Reports, https://gitlab.inria.fr/brain-graph/wl-align/issues
Project-URL: Documentation, https://wl-align.readthedocs.io
Platform: UNKNOWN
Classifier: Development Status :: 4 - Beta
Classifier: Intended Audience :: Science/Research
Classifier: License :: OSI Approved :: MIT License
Classifier: Programming Language :: Python :: 3
Classifier: Topic :: Scientific/Engineering
Requires-Python: >=3
License-File: LICENSE
Requires-Dist: numpy
Requires-Dist: scipy
